pyknex/__init__.py
pyknex/test.py
pyknex-0.0.1.dist-info/METADATA
pyknex-0.0.1.dist-info/WHEEL
pyknex-0.0.1.dist-info/licenses/LICENSE
pyknex-0.0.1.dist-info/RECORD
